ssa_gov/__init__.py
ssa_gov/babynames.py
ssa_gov/utilities.py
ssa_gov-1.0.1.dist-info/METADATA
ssa_gov-1.0.1.dist-info/WHEEL
ssa_gov-1.0.1.dist-info/top_level.txt
ssa_gov-1.0.1.dist-info/RECORD
