Metadata-Version: 2.1
Name: ssa-gov
Version: 1.0.1
Summary: A library enabling users to fetch data from ssa.gov.
Home-page: https://git.octr.is/open-source/data/ssa-gov
Author: Roberto Banić @ Octris LLC
Author-email: roberto@octr.is
Classifier: Programming Language :: Python :: 3
Classifier: License :: OSI Approved :: MIT License
Classifier: Operating System :: OS Independent
Requires-Dist: pandas
Requires-Dist: requests
Requires-Dist: beautifulsoup4
Requires-Dist: html5lib
Requires-Dist: fake-useragent
